taskr/__init__.py
taskr/logs.py
taskr/cli/__init__.py
taskr/cli/common.py
taskr/cli/commands/__init__.py
taskr/cli/commands/add.py
taskr/cli/commands/backup.py
taskr/cli/commands/config.py
taskr/cli/commands/delete.py
taskr/cli/commands/done.py
taskr/cli/commands/info.py
taskr/cli/commands/list.py
taskr/cli/commands/modify.py
taskr/cli/commands/repeat.py
taskr/cli/commands/restore.py
taskr/cli/commands/sync.py
taskr/config/__init__.py
taskr/config/base.py
taskr/config/manager.py
taskr/config/schema.py
taskr/config/syncs.py
taskr/config/utils.py
taskr/interface/__init__.py
taskr/interface/command.py
taskr/interface/export.py
taskr/interface/task.py
taskr/notifications/__init__.py
taskr/sync/__init__.py
taskr/sync/base.py
taskr/sync/reminders/__init__.py
taskr/sync/reminders/core.py
taskr/sync/reminders/manager.py
taskr/sync/reminders/osa.py
taskr/sync/taskd/__init__.py
taskrx-0.2.5.dist-info/METADATA
taskrx-0.2.5.dist-info/WHEEL
taskrx-0.2.5.dist-info/entry_points.txt
taskrx-0.2.5.dist-info/licenses/LICENSE
taskrx-0.2.5.dist-info/RECORD
