Metadata-Version: 2.4
Name: taskrx
Version: 0.2.5
Summary: A CLI wrapper for TaskWarrior with enhanced UX
Project-URL: Documentation, https://github.com/schizoprada/taskr#readme
Project-URL: Source, https://github.com/schizoprada/taskr
Project-URL: Issues, https://github.com/schizoprada/taskr/issues
Author-email: Joel Yisrael <schizoprada@gmail.com>
License-File: LICENSE
Classifier: Development Status :: 3 - Alpha
Classifier: Environment :: Console
Classifier: Intended Audience :: End Users/Desktop
Classifier: License :: OSI Approved :: MIT License
Classifier: Programming Language :: Python :: 3
Classifier: Programming Language :: Python :: 3.8
Classifier: Programming Language :: Python :: 3.9
Classifier: Programming Language :: Python :: 3.10
Classifier: Programming Language :: Python :: 3.11
Classifier: Topic :: Utilities
Requires-Python: >=3.8
Requires-Dist: colorama
Requires-Dist: pydantic>=1.10.0
Requires-Dist: python-dateutil
Requires-Dist: pyyaml>=6.0
Requires-Dist: questionary>=1.10.0
Requires-Dist: rich>=12.6.0
Requires-Dist: typer>=0.7.0
Provides-Extra: dev
Requires-Dist: black>=23.0.0; extra == 'dev'
Requires-Dist: isort>=5.12.0; extra == 'dev'
Requires-Dist: mypy>=1.0.0; extra == 'dev'
Requires-Dist: pre-commit>=3.0.0; extra == 'dev'
Requires-Dist: pytest>=7.0.0; extra == 'dev'
